cutile_gpt/README.md
cutile_gpt/__init__.py
cutile_gpt/api/__init__.py
cutile_gpt/api/config.py
cutile_gpt/api/profiler.py
cutile_gpt/api/tile_op.py
cutile_gpt/examples/__init__.py
cutile_gpt/examples/attention_tile.py
cutile_gpt/examples/gelu_tile.py
cutile_gpt/examples/layernorm_tile.py
cutile_gpt/examples/linear_tile.py
cutile_gpt/kernels/__init__.py
cutile_gpt/kernels/attention.py
cutile_gpt/kernels/embedding.py
cutile_gpt/kernels/fused_mlp.py
cutile_gpt/kernels/gelu.py
cutile_gpt/kernels/layernorm.py
cutile_gpt/kernels/linear.py
cutile_gpt/models/__init__.py
cutile_gpt/models/config.py
cutile_gpt/models/gpt.py
cutile_gpt/utils/__init__.py
cutile_gpt/utils/benchmark.py
cutile_gpt/utils/hf_loader.py
cutile_gpt-0.2.0.dist-info/METADATA
cutile_gpt-0.2.0.dist-info/WHEEL
cutile_gpt-0.2.0.dist-info/licenses/LICENSE
cutile_gpt-0.2.0.dist-info/RECORD
