Metadata-Version: 2.4
Name: cutile-gpt
Version: 0.2.0
Summary: High-performance GPT implementation using NVIDIA CUDA Tile Programming
Project-URL: Homepage, https://github.com/falcons-eyes/cutileGPT
Project-URL: Repository, https://github.com/falcons-eyes/cutileGPT
Project-URL: Documentation, https://github.com/falcons-eyes/cutileGPT#readme
Project-URL: Issues, https://github.com/falcons-eyes/cutileGPT/issues
Project-URL: Changelog, https://github.com/falcons-eyes/cutileGPT/releases
Author-email: Hwoo Joo <falcons.eyes@gmail.com>
License: Apache-2.0
License-File: LICENSE
Keywords: cuda,cupy,deep-learning,gpt,gpu,nvidia,tile-programming,transformer
Classifier: Development Status :: 4 - Beta
Classifier: Environment :: GPU :: NVIDIA CUDA
Classifier: Intended Audience :: Developers
Classifier: Intended Audience :: Science/Research
Classifier: License :: OSI Approved :: Apache Software License
Classifier: Operating System :: POSIX :: Linux
Classifier: Programming Language :: Python :: 3
Classifier: Programming Language :: Python :: 3.13
Classifier: Topic :: Scientific/Engineering :: Artificial Intelligence
Classifier: Topic :: Software Development :: Libraries :: Python Modules
Requires-Python: >=3.13
Requires-Dist: cupy-cuda12x>=13.0.0
Requires-Dist: numpy>=2.0.0
Provides-Extra: all
Requires-Dist: datasets>=3.0.0; extra == 'all'
Requires-Dist: kaleido>=0.2.0; extra == 'all'
Requires-Dist: matplotlib>=3.0.0; extra == 'all'
Requires-Dist: pandas>=2.0.0; extra == 'all'
Requires-Dist: plotly>=5.0.0; extra == 'all'
Requires-Dist: pytest-cov>=4.0.0; extra == 'all'
Requires-Dist: pytest>=8.0.0; extra == 'all'
Requires-Dist: ruff>=0.1.0; extra == 'all'
Requires-Dist: seaborn>=0.13.0; extra == 'all'
Requires-Dist: tiktoken>=0.8.0; extra == 'all'
Requires-Dist: torch>=2.0.0; extra == 'all'
Requires-Dist: transformers>=4.30.0; extra == 'all'
Provides-Extra: dev
Requires-Dist: pytest-cov>=4.0.0; extra == 'dev'
Requires-Dist: pytest>=8.0.0; extra == 'dev'
Requires-Dist: ruff>=0.1.0; extra == 'dev'
Provides-Extra: hf
Requires-Dist: datasets>=3.0.0; extra == 'hf'
Requires-Dist: tiktoken>=0.8.0; extra == 'hf'
Requires-Dist: transformers>=4.30.0; extra == 'hf'
Provides-Extra: torch
Requires-Dist: torch>=2.0.0; extra == 'torch'
Provides-Extra: viz
Requires-Dist: kaleido>=0.2.0; extra == 'viz'
Requires-Dist: matplotlib>=3.0.0; extra == 'viz'
Requires-Dist: pandas>=2.0.0; extra == 'viz'
Requires-Dist: plotly>=5.0.0; extra == 'viz'
Requires-Dist: seaborn>=0.13.0; extra == 'viz'
